LICENSE.txt
MANIFEST.in
README.md
setup.py
BetterSockets/Client.py
BetterSockets/Server.py
BetterSockets/__init__.py
BetterSockets.egg-info/PKG-INFO
BetterSockets.egg-info/SOURCES.txt
BetterSockets.egg-info/dependency_links.txt
BetterSockets.egg-info/top_level.txt
BetterSockets/Asyncio/Client.py
BetterSockets/Asyncio/Hub_Server.py
BetterSockets/Asyncio/Process_Server.py
BetterSockets/Asyncio/__init__.py
BetterSockets/Threads/Client.py
BetterSockets/Threads/Hub_Server.py
BetterSockets/Threads/Process_Server.py
BetterSockets/Threads/__init__.py
Testing/Client.py
Testing/Server.py
venv/Lib/site-packages/_distutils_hack/__init__.py
venv/Lib/site-packages/_distutils_hack/override.py
venv/Lib/site-packages/pip/__init__.py
venv/Lib/site-packages/pip/__main__.py
venv/Lib/site-packages/pip/_internal/__init__.py
venv/Lib/site-packages/pip/_internal/build_env.py
venv/Lib/site-packages/pip/_internal/cache.py
venv/Lib/site-packages/pip/_internal/configuration.py
venv/Lib/site-packages/pip/_internal/exceptions.py
venv/Lib/site-packages/pip/_internal/main.py
venv/Lib/site-packages/pip/_internal/pyproject.py
venv/Lib/site-packages/pip/_internal/self_outdated_check.py
venv/Lib/site-packages/pip/_internal/wheel_builder.py
venv/Lib/site-packages/pip/_internal/cli/__init__.py
venv/Lib/site-packages/pip/_internal/cli/autocompletion.py
venv/Lib/site-packages/pip/_internal/cli/base_command.py
venv/Lib/site-packages/pip/_internal/cli/cmdoptions.py
venv/Lib/site-packages/pip/_internal/cli/command_context.py
venv/Lib/site-packages/pip/_internal/cli/main.py
venv/Lib/site-packages/pip/_internal/cli/main_parser.py
venv/Lib/site-packages/pip/_internal/cli/parser.py
venv/Lib/site-packages/pip/_internal/cli/progress_bars.py
venv/Lib/site-packages/pip/_internal/cli/req_command.py
venv/Lib/site-packages/pip/_internal/cli/spinners.py
venv/Lib/site-packages/pip/_internal/cli/status_codes.py
venv/Lib/site-packages/pip/_internal/commands/__init__.py
venv/Lib/site-packages/pip/_internal/commands/cache.py
venv/Lib/site-packages/pip/_internal/commands/check.py
venv/Lib/site-packages/pip/_internal/commands/completion.py
