Metadata-Version: 2.1
Name: BetterSockets
Version: 0.0.1a7
Summary: Better Python sockets and asyncio streams
Home-page: https://github.com/Drageast/BetterSockets
Author: Luca Michael Schmidt
Author-email: schmidt.lucamichael@gmail.com
License: MIT
Platform: UNKNOWN
Classifier: Development Status :: 3 - Alpha
Classifier: Intended Audience :: Developers 
Classifier: Operating System :: Microsoft :: Windows :: Windows 10
Classifier: License :: OSI Approved :: MIT License
Classifier: Programming Language :: Python :: 3 :: Only
Requires-Python: >=3.6
